kodi_repo_bootstrap/__init__.py
kodi_repo_bootstrap/__main__.py
kodi_repo_bootstrap/addon/__init__.py
kodi_repo_bootstrap/addon/addon.py
kodi_repo_bootstrap/addon/manager.py
kodi_repo_bootstrap/cli/__init__.py
kodi_repo_bootstrap/cli/args.py
kodi_repo_bootstrap/fs/__init__.py
kodi_repo_bootstrap/fs/dir.py
kodi_repo_bootstrap/fs/file.py
kodi_repo_bootstrap/main.py
kodi_repo_bootstrap/repo/__init__.py
kodi_repo_bootstrap/repo/config.py
kodi_repo_bootstrap/repo/manager.py
kodi_repo_bootstrap/repo/version.py
kodi_repo_bootstrap/res/repo_addon.xml.tpl
kodi_repo_bootstrap-3.0.2.dist-info/LICENSE
kodi_repo_bootstrap-3.0.2.dist-info/METADATA
kodi_repo_bootstrap-3.0.2.dist-info/WHEEL
kodi_repo_bootstrap-3.0.2.dist-info/entry_points.txt
kodi_repo_bootstrap-3.0.2.dist-info/RECORD
