Metadata-Version: 2.1
Name: kodi-repo-bootstrap
Version: 3.0.2
Summary: Bootstrap GIT repo for setting up a Kodi repository
Home-page: https://github.com/mammo0/kodi-repo-bootstrap
License: GPL-2.0-only
Author: mammo0
Author-email: marc.ammon@hotmail.de
Requires-Python: >=3.8,<4.0
Classifier: License :: OSI Approved :: GNU General Public License v2 (GPLv2)
Classifier: Programming Language :: Python :: 3
Classifier: Programming Language :: Python :: 3.8
Classifier: Programming Language :: Python :: 3.9
Classifier: Programming Language :: Python :: 3.10
Classifier: Programming Language :: Python :: 3.11
Classifier: Programming Language :: Python :: 3.12
